<?xml version="1.0"?>
<!DOCTYPE hibernate-mapping PUBLIC "-//Hibernate/Hibernate Mapping DTD 3.0//EN"
"http://hibernate.sourceforge.net/hibernate-mapping-3.0.dtd">
<!-- Generated 2012-9-8 14:04:53 by Hibernate Tools 3.4.0.CR1 -->
<hibernate-mapping>
    <class name="com.jshop.entity.RoleT" table="role_t" catalog="jshopactive">
        <id name="roleid" type="string">
            <column name="ROLEID" length="20" />
            <generator class="assigned" />
        </id>
        <property name="rolename" type="string">
            <column name="ROLENAME" length="45" not-null="true" />
        </property>
        <property name="note" type="string">
            <column name="NOTE" length="100" not-null="true" />
        </property>
        <property name="createtime" type="timestamp">
            <column name="CREATETIME" length="0" not-null="true" />
        </property>
        <property name="creatorid" type="string">
            <column name="CREATORID" length="20" not-null="true" />
        </property>
    </class>
</hibernate-mapping>
